gym_maze/__init__.py
gym_maze/envs/__init__.py
gym_maze/envs/maze.py
gym_maze/envs/maze_env.py
gym_maze/envs/maze_view_2d.py
gym_maze/envs/samples/maze2d_100x100.npy
gym_maze/envs/samples/maze2d_10x10.npy
gym_maze/envs/samples/maze2d_25x25.npy
gym_maze/envs/samples/maze2d_50x50.npy
gym_maze/envs/samples/maze2d_5x5.npy
gym_maze_trustycoder83-0.0.4.dist-info/LICENSE
gym_maze_trustycoder83-0.0.4.dist-info/METADATA
gym_maze_trustycoder83-0.0.4.dist-info/WHEEL
gym_maze_trustycoder83-0.0.4.dist-info/top_level.txt
gym_maze_trustycoder83-0.0.4.dist-info/RECORD
