Metadata-Version: 2.1
Name: gym-maze-trustycoder83
Version: 0.0.4
Summary: A simple 2D maze environment for OpenAI Gym
Home-page: https://github.com/pyscaffold/pyscaffold/
Author: Trusty Coder
Author-email: trustycoder83@gmail.com
License: MIT
Platform: any
Classifier: Intended Audience :: Developers
Classifier: Environment :: GPU
Classifier: Development Status :: 3 - Alpha
Classifier: Programming Language :: Python :: 3.6
Classifier: Programming Language :: Python :: 3.7
Classifier: License :: OSI Approved :: MIT License
Classifier: Operating System :: OS Independent
Requires-Python: <3.8,>=3.6
Requires-Dist: numpy (==1.18.5)
Requires-Dist: pygame (==1.9.6)
Requires-Dist: gym (==0.17.2)
